{"0": ["38", "28", "72", "22"], "1": ["37", "79", "71"], "10": ["7", "113", "43", "31"], "100": ["67", "47", "98", "64"], "101": ["91", "75", "75"], "102": ["83", "22", "6"], "103": ["71", "42", "115"], "104": ["23", "25", "13", "6"], "105": ["70"], "106": ["107", "19", "48", "94"], "107": ["12", "34", "106", "49"], "108": ["21", "21"], "109": ["4", "98"], "11": ["86", "113", "69", "24"], "110": ["60", "61"], "111": ["90", "45", "51", "95"], "112": ["2", "34", "59"], "113": ["10", "73", "11"], "114": ["86", "43", "86", "34"], "115": ["103", "27", "8"], "116": ["89", "26", "66"], "12": ["48", "107", "94", "94"], "13": ["91", "104", "23", "21"], "14": ["37", "26", "80", "39"], "15": ["76", "45", "78"], "16": ["68", "18", "80", "36"], "17": ["2", "93", "54"], "18": ["16", "56"], "19": ["48", "94", "106"], "2": ["112", "17", "54"], "20": [], "21": ["108", "13", "73", "108"], "22": ["72", "102", "0", "43"], "23": ["104", "25", "13"], "24": ["11", "76", "45", "77"], "25": ["104", "23"], "26": ["79", "14", "87", "116"], "27": ["74", "115", "63"], "28": ["0", "51", "90", "62"], "29": [], "3": ["78", "76", "95", "6"], "30": ["9", "62", "57", "41"], "31": ["10", "73", "7", "69"], "32": ["84", "84", "41"], "33": ["42", "71", "87"], "34": ["107", "48", "112", "114"], "35": ["52", "99"], "36": ["66", "96", "89", "16"], "37": ["1", "90", "14", "78"], "38": ["0", "72", "90", "51"], "39": ["14", "66", "8", "44"], "4": ["109", "97", "67", "7"], "40": [], "41": ["50", "56", "32", "30"], "42": ["103", "33"], "43": ["10", "69", "114", "22"], "44": ["49", "49", "39", "53"], "45": ["111", "92", "15", "24"], "46": [], "47": ["82", "68", "96", "100"], "48": ["12", "19", "106", "34"], "49": ["44", "107", "44", "53"], "5": ["9", "82", "62"], "50": ["84", "41"], "51": ["111", "38", "78", "28"], "52": ["35"], "53": ["87", "49", "44"], "54": ["66", "17", "2"], "55": ["61"], "56": ["18", "89", "89", "41"], "57": ["98", "97", "30", "6"], "58": ["65"], "59": ["112", "60", "70"], "6": ["102", "104", "57", "3"], "60": ["93", "110", "59"], "61": ["110", "55"], "62": ["30", "28", "88", "5"], "63": ["74", "27", "87"], "64": ["9", "68", "82", "100"], "65": ["58"], "66": ["36", "54", "39", "116"], "67": ["68", "100", "4"], "68": ["16", "67", "64", "47"], "69": ["11", "43", "31"], "7": ["10", "73", "31", "4"], "70": ["59", "105"], "71": ["103", "1", "8", "33"], "72": ["77", "0", "38", "22"], "73": ["113", "7", "31", "21"], "74": ["8", "63", "27"], "75": ["91", "101", "101"], "76": ["95", "15", "3", "24"], "77": ["95", "92", "72", "24"], "78": ["3", "51", "15", "37"], "79": ["26", "1"], "8": ["74", "71", "115", "39"], "80": ["16", "88", "14", "86"], "81": [], "82": ["5", "47", "96", "64"], "83": ["102"], "84": ["32", "50", "32"], "85": [], "86": ["11", "114", "114", "80"], "87": ["26", "63", "33", "53"], "88": ["9", "96", "62", "80"], "89": ["56", "56", "116", "36"], "9": ["88", "30", "5", "64"], "90": ["111", "38", "28", "37"], "91": ["101", "75", "13"], "92": ["77", "45"], "93": ["17", "60"], "94": ["19", "12", "12", "106"], "95": ["77", "76", "111", "3"], "96": ["88", "47", "82", "36"], "97": ["4", "98", "57"], "98": ["97", "109", "57", "100"], "99": ["35"]}