{"0": [], "1": ["8", "55", "78", "73"], "10": ["22", "36"], "11": ["38", "68", "38"], "12": ["80", "23"], "13": [], "14": ["30", "49", "30"], "15": ["2", "61"], "16": ["88", "21", "4", "39"], "17": [], "18": [], "19": ["30", "27", "49"], "2": ["36", "15", "39"], "20": ["82"], "21": ["8", "56", "4", "16"], "22": ["10", "42", "90"], "23": ["12", "33", "35", "62"], "24": ["78", "58", "58", "70"], "25": ["70"], "26": ["47", "3", "89"], "27": ["4", "9", "19", "61"], "28": ["37", "89"], "29": ["68", "95", "38"], "3": ["54", "26"], "30": ["14", "19", "14", "61"], "31": [], "32": ["62"], "33": ["80", "72", "23"], "34": ["44", "73"], "35": ["9", "23", "5", "88"], "36": ["10", "2", "90", "70"], "37": ["28", "54"], "38": ["11", "11", "29", "75"], "39": ["56", "16", "2", "90"], "4": ["27", "50", "21", "16"], "40": ["63", "48", "92"], "41": ["77"], "42": ["55", "66", "22", "62"], "43": [], "44": ["34", "68", "45"], "45": ["44"], "46": ["89", "82"], "47": ["26", "72"], "48": ["74", "40", "75"], "49": ["19", "14"], "5": ["35", "64"], "50": ["71", "4", "9", "79"], "51": ["77"], "52": [], "53": [], "54": ["37", "3", "62"], "55": ["1", "71", "42", "79"], "56": ["39", "67", "8", "21"], "57": ["93"], "58": ["78", "24", "24", "70"], "59": ["95", "60"], "6": ["74", "73"], "60": ["59"], "61": ["15", "68", "27", "30"], "62": ["23", "42", "54", "32"], "63": ["40", "76"], "64": ["88", "5", "91"], "65": [], "66": ["8", "71", "42", "79"], "67": ["71", "56"], "68": ["11", "29", "44", "61"], "69": ["83", "93"], "7": [], "70": ["58", "25", "36", "24"], "71": ["50", "55", "66", "67"], "72": ["33", "47"], "73": ["6", "34", "1"], "74": ["48", "86", "6"], "75": ["92", "95", "48", "38"], "76": ["92", "63"], "77": ["41", "51", "80", "87"], "78": ["1", "24", "58"], "79": ["88", "55", "50", "66"], "8": ["1", "21", "66", "56"], "80": ["12", "33", "9", "77"], "81": [], "82": ["20", "46"], "83": ["69", "93"], "84": [], "85": ["90"], "86": ["74"], "87": ["77"], "88": ["79", "16", "64", "35"], "89": ["28", "26", "46"], "9": ["80", "50", "27", "35"], "90": ["22", "36", "85", "39"], "91": ["64"], "92": ["40", "76", "75"], "93": ["69", "57", "83"], "94": [], "95": ["59", "29", "75"]}