{"0": [], "1": ["92", "54", "16", "109"], "10": ["71", "77", "60"], "100": ["22", "95", "2", "19"], "101": ["47", "44"], "102": ["91", "5", "63"], "103": ["25", "73", "90"], "104": ["59", "24", "53"], "105": ["37", "34", "74", "7"], "106": ["42", "62", "32", "51"], "107": ["17", "85"], "108": ["56", "38", "90"], "109": ["92", "31", "65", "1"], "11": ["71", "84", "33"], "12": ["93", "78"], "13": ["46", "18", "34", "36"], "14": ["71", "77", "34"], "15": ["96", "63"], "16": ["73", "45", "1", "65"], "17": ["85", "107", "85"], "18": ["84", "13", "26", "33"], "19": ["89", "99", "22", "100"], "2": ["100", "95"], "20": ["82", "82"], "21": ["66", "49"], "22": ["89", "100", "19"], "23": ["43", "46"], "24": ["53", "104", "59", "53"], "25": ["94", "99", "103", "35"], "26": ["60", "40", "18"], "27": [], "28": ["98"], "29": ["62", "51", "42", "32"], "3": ["54", "5", "41", "91"], "30": ["61", "59", "61"], "31": ["92", "109", "94", "39"], "32": ["106", "62", "76", "29"], "33": ["77", "41", "11", "18"], "34": ["105", "13", "14"], "35": ["25", "39", "73", "38"], "36": ["13", "70", "4", "86"], "37": ["96", "105", "7"], "38": ["45", "108", "8", "35"], "39": ["35", "45", "54", "31"], "4": ["70", "69", "36"], "40": ["41", "26"], "41": ["71", "40", "33", "3"], "42": ["106", "29", "46"], "43": ["76", "51", "23"], "44": ["101", "79", "48", "80"], "45": ["16", "65", "39", "38"], "46": ["23", "42", "13"], "47": ["101", "79", "79", "80"], "48": ["44", "60"], "49": ["66", "21", "87"], "5": ["3", "6", "102", "6"], "50": [], "51": ["106", "43", "76", "29"], "52": ["55", "55", "55"], "53": ["24", "92", "104", "24"], "54": ["1", "39", "56", "3"], "55": ["52", "52", "52"], "56": ["108", "99", "54"], "57": [], "58": ["75"], "59": ["104", "24", "30"], "6": ["91", "67", "5", "5"], "60": ["10", "26", "84", "48"], "61": ["30", "30"], "62": ["106", "32", "29"], "63": ["102", "67", "96", "15"], "64": [], "65": ["45", "109", "16", "74"], "66": ["21", "87", "49"], "67": ["6", "63"], "68": ["80", "80", "83"], "69": ["86", "4"], "7": ["105", "37"], "70": ["4", "86", "36"], "71": ["14", "10", "41", "11"], "72": [], "73": ["103", "8", "16", "35"], "74": ["76", "65", "91", "105"], "75": ["58"], "76": ["43", "32", "51", "74"], "77": ["10", "14", "33", "84"], "78": ["93", "12", "93"], "79": ["47", "44", "47"], "8": ["73", "99", "81", "38"], "80": ["47", "44", "68", "68"], "81": ["94", "90", "8"], "82": ["20", "20"], "83": ["68"], "84": ["18", "11", "60", "77"], "85": ["17", "107", "17"], "86": ["69", "70", "36"], "87": ["66", "49"], "88": [], "89": ["90", "22", "95", "19"], "9": [], "90": ["81", "108", "103", "89"], "91": ["102", "6", "3", "74"], "92": ["1", "109", "31", "53"], "93": ["78", "12", "78"], "94": ["25", "31", "81", "95"], "95": ["89", "100", "94", "2"], "96": ["37", "63", "15"], "97": [], "98": ["28"], "99": ["25", "8", "56", "19"]}