{"0": ["26", "63", "63", "99"], "1": ["11", "89", "27", "51"], "10": ["89", "54", "51", "107"], "100": ["86", "70", "99"], "101": [], "102": ["7", "43", "108"], "103": [], "104": ["69", "79"], "105": ["48", "76"], "106": ["39", "67"], "107": ["83", "10", "27", "83"], "108": ["7", "102", "92", "93"], "109": ["54", "87", "94"], "11": ["1", "89", "2"], "12": ["15", "33", "20", "6"], "13": ["91", "65", "85", "65"], "14": ["79", "69", "96", "96"], "15": ["12", "20"], "16": ["83", "9"], "17": ["42", "2", "28"], "18": ["39", "24", "24", "99"], "19": ["28"], "2": ["97", "11", "17"], "20": ["33", "15", "12", "33"], "21": ["26", "99"], "22": ["41", "41", "57"], "23": ["66", "66"], "24": ["18", "18", "6", "91"], "25": ["73", "29", "77"], "26": ["0", "21", "63"], "27": ["1", "54", "51", "107"], "28": ["19", "17"], "29": ["57", "41", "25", "32"], "3": ["36", "78", "49"], "30": ["62", "59", "59", "62"], "31": ["52", "56", "74", "5"], "32": ["29", "77", "73", "61"], "33": ["20", "12", "20", "6"], "34": ["6", "53", "63", "53"], "35": ["86", "70"], "36": ["91", "74", "3"], "37": ["82", "70", "53", "4"], "38": ["68", "68", "8", "40"], "39": ["106", "52", "56", "18"], "4": ["82", "37", "85"], "40": ["86", "68", "86", "38"], "41": ["22", "57", "29", "22"], "42": ["17"], "43": ["72", "102", "97", "92"], "44": [], "45": ["55", "55"], "46": [], "47": [], "48": ["76", "105", "92", "76"], "49": ["70", "3"], "5": ["52", "74", "56", "31"], "50": ["60", "60", "60"], "51": ["27", "89", "1", "10"], "52": ["31", "39", "5", "56"], "53": ["34", "34", "82", "37"], "54": ["27", "10", "109", "94"], "55": ["45", "45", "95"], "56": ["31", "39", "5", "52"], "57": ["29", "41", "61", "22"], "58": ["9"], "59": ["30", "62", "30"], "6": ["12", "33", "24", "34"], "60": ["50", "50", "50"], "61": ["57", "73", "77", "32"], "62": ["30", "59", "30"], "63": ["0", "0", "26", "34"], "64": [], "65": ["85", "13", "91", "13"], "66": ["23", "23"], "67": ["106"], "68": ["38", "8", "38", "40"], "69": ["14", "104"], "7": ["72", "108", "102", "97"], "70": ["35", "100", "37", "49"], "71": [], "72": ["7", "92", "43"], "73": ["25", "77", "32", "61"], "74": ["31", "5", "36"], "75": [], "76": ["48", "105", "48"], "77": ["25", "32", "73", "61"], "78": ["3"], "79": ["14", "104"], "8": ["68", "38"], "80": ["87", "94", "81"], "81": ["94", "87", "80"], "82": ["4", "37", "53"], "83": ["107", "16", "107"], "84": [], "85": ["65", "13", "4"], "86": ["35", "100", "40", "40"], "87": ["80", "81", "109"], "88": [], "89": ["10", "11", "1", "51"], "9": ["16", "58"], "90": [], "91": ["13", "65", "36", "24"], "92": ["72", "43", "108", "48"], "93": ["97", "108"], "94": ["81", "80", "109", "54"], "95": ["55"], "96": ["14", "14"], "97": ["7", "43", "2", "93"], "98": [], "99": ["21", "0", "100", "18"]}